[
	{
		"name": "2d_mixed_histogram",
		"title": "2D Mixed Histogram",
		"attributes": ["categorical", "numerical"],
		"scale": "mix_histogram"
	},
	{
		"name": "1d_categorical_histogram",
		"title": "1D Categorical Histogram",
		"attributes": ["categorical"],
		"scale": "naive_categorical1d"
	},
	{
		"name": "1d_numerical_histogram",
		"title": "1D Numerical Histogram",
		"attributes": ["numerical"],
		"scale": "naive_numerical1d"
	},
	{
		"name": "2d_numerical_histogram",
		"title": "2D Numerical Histogram",
		"attributes": ["numerical", "numerical"],
		"scale": "multi_numerical_histogram"
	}, {
		"name": "2d_categorical_histogram",
		"title": "2D Categorical Histogram",
		"attributes": ["categorical", "categorical"],
		"scale": "multi_categorical_histogram"
	},
	{
		"name": "secure_aggregation",
		"title": "Aggregation",
		"attributes": ["numerical"],
		"scale": ""
	}
]
